diceplayer/__init__.py
diceplayer/__main__.py
diceplayer/player.py
diceplayer/shared/__init__.py
diceplayer/shared/config/__init__.py
diceplayer/shared/config/dice_config.py
diceplayer/shared/config/gaussian_config.py
diceplayer/shared/config/player_config.py
diceplayer/shared/environment/__init__.py
diceplayer/shared/environment/atom.py
diceplayer/shared/environment/molecule.py
diceplayer/shared/environment/system.py
diceplayer/shared/interface/__init__.py
diceplayer/shared/interface/__interface.py
diceplayer/shared/interface/dice_interface.py
diceplayer/shared/interface/gaussian_interface.py
diceplayer/shared/utils/__init__.py
diceplayer/shared/utils/dataclass_protocol.py
diceplayer/shared/utils/logger.py
diceplayer/shared/utils/misc.py
diceplayer/shared/utils/ptable.py
diceplayer-1.1a0.dist-info/METADATA
diceplayer-1.1a0.dist-info/WHEEL
diceplayer-1.1a0.dist-info/entry_points.txt
diceplayer-1.1a0.dist-info/RECORD
